{"arcana": "Void", "cutinfo": {"1_42": "Maymays."}, "cutscenes": {"10_15": {"id": "Void10_15", "items": [[{"text": "Test info 1"}]]}, "10_5": {"id": "Void10_5", "items": [[{"text": "Test info 1"}]]}, "1_0": {"id": "Void1_0", "items": [[{"text": "Info 1"}, 1], [{"text": "Info 2"}, 2], [{"text": "Info 3"}, 3], [{"text": "Info 4"}, 4], [{"text": "Test info 5"}, 2, 1]]}, "1_42": {"id": "Void1_42", "items": [[{"text": "Action 1"}]]}, "2_0": {"id": "Void2_0", "items": [[{"text": "Action 1"}, 1, 2], [{"text": "Action 2"}], [{"text": "Action 3"}, 3], [{"text": "Action 4"}, 1]]}}, "finalpersona": {"15": "Seraph", "5": "Jack Frost"}, "info": "Gotta meme fast!", "pseudoname": "Chaos", "requiredPoints": {"1": {"0": {"acad": 1, "charm": 4, "courage": 1, "points": 5}, "42": {"acad": 1, "charm": 1, "courage": 3, "points": 98}}, "2": {"0": {"acad": 4, "charm": 3, "courage": 2, "points": 5}}}}